ctxzippy/__init__.py
ctxzippy/compact.py
ctxzippy/adapters/__init__.py
ctxzippy/adapters/base.py
ctxzippy/adapters/filesystem.py
ctxzippy/adapters/s3.py
ctxzippy/storage/__init__.py
ctxzippy/storage/grep.py
ctxzippy/storage/known_keys.py
ctxzippy/storage/resolver.py
ctxzippy/strategies/__init__.py
ctxzippy/strategies/write_tool_results.py
ctxzippy/tools/__init__.py
ctxzippy/tools/grep.py
ctxzippy/tools/reader.py
ctxzippy-0.1.0.dist-info/licenses/LICENSE
ctxzippy-0.1.0.dist-info/METADATA
ctxzippy-0.1.0.dist-info/WHEEL
ctxzippy-0.1.0.dist-info/top_level.txt
ctxzippy-0.1.0.dist-info/RECORD
