Metadata-Version: 2.4
Name: ctxzippy
Version: 0.1.0
Summary: A Python library for compacting large tool-call results in conversation histories
Author-email: Richard S <rscheiwe.dev@gmail.com>
Maintainer-email: Richard S <rscheiwe.dev@gmail.com>
License: MIT
Project-URL: Homepage, https://github.com/rscheiwe/ctx-zip-py
Project-URL: Bug Tracker, https://github.com/rscheiwe/ctx-zip-py/issues
Project-URL: Documentation, https://github.com/rscheiwe/ctx-zip-py#readme
Keywords: context,compression,ai,llm,tool-calls,storage
Classifier: Development Status :: 4 - Beta
Classifier: Intended Audience :: Developers
Classifier: License :: OSI Approved :: MIT License
Classifier: Programming Language :: Python :: 3
Classifier: Programming Language :: Python :: 3.8
Classifier: Programming Language :: Python :: 3.9
Classifier: Programming Language :: Python :: 3.10
Classifier: Programming Language :: Python :: 3.11
Classifier: Programming Language :: Python :: 3.12
Classifier: Topic :: Software Development :: Libraries :: Python Modules
Classifier: Topic :: Text Processing
Requires-Python: >=3.8
License-File: LICENSE
Provides-Extra: dev
Requires-Dist: pytest>=7.0; extra == "dev"
Requires-Dist: pytest-asyncio>=0.21; extra == "dev"
Requires-Dist: pytest-cov>=4.0; extra == "dev"
Requires-Dist: black>=23.0; extra == "dev"
Requires-Dist: mypy>=1.0; extra == "dev"
Requires-Dist: ruff>=0.1; extra == "dev"
Provides-Extra: s3
Requires-Dist: boto3>=1.26; extra == "s3"
Dynamic: license-file
